cube_practicer/PLL.py
cube_practicer/__init__.py
cube_practicer/__main__.py
cube_practicer/main.py
cube_practicer/resources/UbuntuMono-R.ttf
cube_practicer-0.0.2.dist-info/entry_points.txt
cube_practicer-0.0.2.dist-info/WHEEL
cube_practicer-0.0.2.dist-info/METADATA
cube_practicer-0.0.2.dist-info/RECORD
